speech4t/__init__.py
speech4t/common.py
語音模組/__init__.py
speech4t-0.0.6.dist-info/LICENSE
speech4t-0.0.6.dist-info/METADATA
speech4t-0.0.6.dist-info/WHEEL
speech4t-0.0.6.dist-info/top_level.txt
speech4t-0.0.6.dist-info/RECORD
