Metadata-Version: 2.1
Name: speech4t
Version: 0.0.6
Summary: Speech wrapper library for Teenagers
Home-page: https://github.com/beardad1975/speech4t
Author: Wen-Hung, Chang 張文宏
Author-email: beardad1975@nmes.tyc.edu.tw
Platform: Windows
Classifier: Programming Language :: Python :: 3
Classifier: License :: OSI Approved :: MIT License
Classifier: Operating System :: Microsoft :: Windows
Classifier: Natural Language :: Chinese (Traditional)
Requires-Python: >=3.8
License-File: LICENSE
Requires-Dist: pywin32 (>=305)
Requires-Dist: SpeechRecognition (>=3.9.0)
